gridinfo/__init__.py
gridinfo/__main__.py
gridinfo/app.py
gridinfo/card.py
gridinfo/getter.py
gridinfo/gridinfo.css
gridinfo/gridsurvey.py
gridinfo/main_screen.py
gridinfo/py.typed
gridinfo/region_info.py
gridinfo/sl_api.py
gridinfo/unpacker.py
gridinfo-0.1.0.dist-info/LICENSE
gridinfo-0.1.0.dist-info/METADATA
gridinfo-0.1.0.dist-info/WHEEL
gridinfo-0.1.0.dist-info/entry_points.txt
gridinfo-0.1.0.dist-info/top_level.txt
gridinfo-0.1.0.dist-info/RECORD
